AUTHORS.rst
LICENSE.txt
MANIFEST.in
README.rst
VERSION.txt
setup.cfg
setup.py
tests/test_asian_font_support.py
tests/test_css_media_rule.py
tests/test_document.py
tests/test_http.py
tests/test_paragraph.py
tests/test_parser.py
tests/test_reportlab.py
tests/test_right_to_left_font_support.py
tests/test_selectors.py
tests/test_special_css.py
tests/test_table_css.py
tests/test_tables.py
tests/test_tags.py
tests/test_update_face_name.py
tests/test_utils.py
xhtml2pdf/__init__.py
xhtml2pdf/charts.py
xhtml2pdf/context.py
xhtml2pdf/default.py
xhtml2pdf/document.py
xhtml2pdf/files.py
xhtml2pdf/paragraph.py
xhtml2pdf/parser.py
xhtml2pdf/pdf.py
xhtml2pdf/pisa.py
xhtml2pdf/reportlab_paragraph.py
xhtml2pdf/tables.py
xhtml2pdf/tags.py
xhtml2pdf/util.py
xhtml2pdf/wsgi.py
xhtml2pdf/xhtml2pdf_reportlab.py
xhtml2pdf/builders/__init__.py
xhtml2pdf/builders/signs.py
xhtml2pdf/builders/watermarks.py
xhtml2pdf/config/__init__.py
xhtml2pdf/config/httpconfig.py
xhtml2pdf/w3c/__init__.py
xhtml2pdf/w3c/css.py
xhtml2pdf/w3c/cssDOMElementInterface.py
xhtml2pdf/w3c/cssParser.py
xhtml2pdf/w3c/cssSpecial.py
xhtml2pdf2.egg-info/PKG-INFO
xhtml2pdf2.egg-info/SOURCES.txt
xhtml2pdf2.egg-info/dependency_links.txt
xhtml2pdf2.egg-info/entry_points.txt
xhtml2pdf2.egg-info/requires.txt
xhtml2pdf2.egg-info/top_level.txt